plover_1password/__init__.py
plover_1password/__version__.py
plover_1password/extension.py
plover_1password/secret/__init__.py
plover_1password/secret/client.py
plover_1password/secret/error.py
plover_1password/secret/resolver.py
plover_1password/secret_reference/__init__.py
plover_1password/secret_reference/expander.py
plover_1password/service_account/__init__.py
plover_1password/service_account/token.py
plover_1password/shell_command/__init__.py
plover_1password/shell_command/resolver.py
plover_1password/shell_command/runner.py
plover_1password-0.4.2.dist-info/LICENSE.txt
plover_1password-0.4.2.dist-info/METADATA
plover_1password-0.4.2.dist-info/WHEEL
plover_1password-0.4.2.dist-info/entry_points.txt
plover_1password-0.4.2.dist-info/top_level.txt
plover_1password-0.4.2.dist-info/zip-safe
plover_1password-0.4.2.dist-info/RECORD
